Products.Poi-4.0.3-py3.8-nspkg.pth
Products/Poi/TODO.txt
Products/Poi/__init__.py
Products/Poi/adapters.py
Products/Poi/config.py
Products/Poi/configure.zcml
Products/Poi/events.py
Products/Poi/indexers.py
Products/Poi/interfaces.py
Products/Poi/migration.py
Products/Poi/permissions.py
Products/Poi/permissions.zcml
Products/Poi/profiles.zcml
Products/Poi/rebuild_i18n.sh
Products/Poi/setuphandlers.py
Products/Poi/utils.py
Products/Poi/widgets.py
Products/Poi/Extensions/install.py
Products/Poi/browser/__init__.py
Products/Poi/browser/configure.zcml
Products/Poi/browser/exporter.py
Products/Poi/browser/interfaces.py
Products/Poi/browser/issue.py
Products/Poi/browser/issue_uploads.pt
Products/Poi/browser/log.pt
Products/Poi/browser/log.py
Products/Poi/browser/notifications.py
Products/Poi/browser/notifications.zcml
Products/Poi/browser/related_popup.pt
Products/Poi/browser/response.pt
Products/Poi/browser/response.py
Products/Poi/browser/tracker.py
Products/Poi/browser/watchers.py
Products/Poi/browser/resources/PoiIssue.gif
Products/Poi/browser/resources/PoiTracker.gif
Products/Poi/browser/resources/attachment.png
Products/Poi/browser/resources/poi-email.css
Products/Poi/browser/resources/poi-resources-compiled.css
Products/Poi/browser/resources/poi-resources-compiled.js
Products/Poi/browser/resources/poi.css
Products/Poi/browser/resources/poi.js
Products/Poi/browser/templates/edit_response.pt
Products/Poi/browser/templates/poi-issue-search-rss.xml.pt
Products/Poi/browser/templates/poi-my-issues-rss.xml.pt
Products/Poi/browser/templates/poi-my-submitted-issues-rss.xml.pt
Products/Poi/browser/templates/poi-orphaned-issues-rss.xml.pt
Products/Poi/browser/templates/poi_email_new_issue_html.pt
Products/Poi/browser/templates/poi_email_new_issue_plain.pt
Products/Poi/browser/templates/poi_email_new_response_html.pt
Products/Poi/browser/templates/poi_email_new_response_plain.pt
Products/Poi/browser/templates/poi_email_resolved_issue_html.pt
Products.Poi-4.0.3.dist-info/METADATA
Products.Poi-4.0.3.dist-info/WHEEL
Products.Poi-4.0.3.dist-info/entry_points.txt
Products.Poi-4.0.3.dist-info/namespace_packages.txt
Products.Poi-4.0.3.dist-info/top_level.txt
Products.Poi-4.0.3.dist-info/RECORD
