Metadata-Version: 2.1
Name: Products.Poi
Version: 4.0.3
Summary: Poi: A friendly issue tracker
Home-page: http://plone.org/products/poi
Author: Martin Aspeli
Author-email: plone-users@lists.sourceforge.net
License: GPL
Keywords: bugs issue tracker
Platform: UNKNOWN
Classifier: Framework :: Plone
Classifier: Framework :: Plone :: 5.0
Classifier: Framework :: Zope2
Classifier: Framework :: Zope3
Classifier: Programming Language :: Python
Classifier: Programming Language :: Python :: 2.7
Classifier: Topic :: Software Development :: Libraries :: Python Modules
Requires-Dist: setuptools
Requires-Dist: plone.app.blob
Requires-Dist: plone.namedfile
Requires-Dist: Products.CMFPlone (>=5.0.5)
Requires-Dist: collective.dexteritytextindexer
Requires-Dist: collective.watcherlist (>=3.0)
Requires-Dist: collective.z3cform.datagridfield
Requires-Dist: Products.OrderableReferenceField
Requires-Dist: plone.app.referenceablebehavior
Requires-Dist: plone.app.relationfield (>=1.3.4)
Provides-Extra: test
Requires-Dist: Products.PloneTestCase ; extra == 'test'
